trace_extractor/__init__.py
trace_extractor/__main__.py
trace_extractor/app.py
trace_extractor/args.py
trace_extractor/data_extract.py
trace_extractor/data_transform.py
trace_extractor-0.0.3.dist-info/LICENSE
trace_extractor-0.0.3.dist-info/METADATA
trace_extractor-0.0.3.dist-info/WHEEL
trace_extractor-0.0.3.dist-info/entry_points.txt
trace_extractor-0.0.3.dist-info/top_level.txt
trace_extractor-0.0.3.dist-info/RECORD
