Metadata-Version: 2.1
Name: trace-extractor
Version: 0.0.3
Summary: MPEG-4 Trace extractor for ns-3
Home-page: https://github.com/FtZPetruska/trace_extractor
Author: Pierre Wendling
Author-email: pierre.wendling.4@gmail.com
License: GPLv3
Project-URL: Bug Tracker, https://github.com/FtZPetruska/trace_extractor
Classifier: Programming Language :: Python :: 3 :: Only
Classifier: Programming Language :: Python :: 3.9
Classifier: Programming Language :: Python :: 3.10
Classifier: Programming Language :: Python :: 3.11
Classifier: Environment :: Console
Classifier: License :: OSI Approved :: GNU General Public License v3 (GPLv3)
Classifier: Operating System :: OS Independent
Requires-Python: >=3.9
License-File: LICENSE
